foreqast/__init__.py
foreqast/client.py
foreqast/vrp/__init__.py
foreqast/vrp/data_types.py
foreqast/vrp/utils.py
foreqast/vrp/vrp.py
foreqast_client-1.0.0.dist-info/METADATA
foreqast_client-1.0.0.dist-info/WHEEL
foreqast_client-1.0.0.dist-info/top_level.txt
foreqast_client-1.0.0.dist-info/RECORD
